hi_lsiwh37249/__init__.py
hi_lsiwh37249/hello.py
hi_lsiwh37249-0.7.0.dist-info/METADATA
hi_lsiwh37249-0.7.0.dist-info/WHEEL
hi_lsiwh37249-0.7.0.dist-info/entry_points.txt
hi_lsiwh37249-0.7.0.dist-info/top_level.txt
hi_lsiwh37249-0.7.0.dist-info/RECORD
